pyshark/__init__.py
pyshark/cache.py
pyshark/config.ini
pyshark/config.py
pyshark/ek_field_mapping.py
pyshark/capture/__init__.py
pyshark/capture/capture.py
pyshark/capture/file_capture.py
pyshark/capture/inmem_capture.py
pyshark/capture/live_capture.py
pyshark/capture/live_ring_capture.py
pyshark/capture/pipe_capture.py
pyshark/capture/remote_capture.py
pyshark/packet/__init__.py
pyshark/packet/common.py
pyshark/packet/consts.py
pyshark/packet/fields.py
pyshark/packet/packet.py
pyshark/packet/packet_summary.py
pyshark/packet/layers/__init__.py
pyshark/packet/layers/base.py
pyshark/packet/layers/ek_layer.py
pyshark/packet/layers/json_layer.py
pyshark/packet/layers/xml_layer.py
pyshark/tshark/__init__.py
pyshark/tshark/tshark.py
pyshark/tshark/output_parser/__init__.py
pyshark/tshark/output_parser/base_parser.py
pyshark/tshark/output_parser/tshark_ek.py
pyshark/tshark/output_parser/tshark_json.py
pyshark/tshark/output_parser/tshark_xml.py
pyshark-0.5.3.dist-info/METADATA
pyshark-0.5.3.dist-info/WHEEL
pyshark-0.5.3.dist-info/top_level.txt
pyshark-0.5.3.dist-info/RECORD
