Metadata-Version: 1.1
Name: pyshark
Version: 0.5.3
Summary: Python wrapper for tshark, allowing python packet parsing using wireshark dissectors
Home-page: https://github.com/KimiNewt/pyshark
Author: KimiNewt
Author-email: UNKNOWN
License: MIT
Keywords: wireshark capture packets parsing packet
Platform: UNKNOWN
Classifier: License :: OSI Approved :: MIT License
Classifier: Programming Language :: Python :: 3.5
Classifier: Programming Language :: Python :: 3.6
Classifier: Programming Language :: Python :: 3.7
Classifier: Programming Language :: Python :: 3.8
Classifier: Programming Language :: Python :: 3.9
Classifier: Programming Language :: Python :: 3.10
